polkadots
