Metadata-Version: 1.1
Name: polkadots-dotfile-manager
Version: 0.0.5
Summary: Yet another dotfile manager
Home-page: https://github.com/lf-/polkadots
Author: lf
Author-email: p}thon@lfcode.ca
License: MIT
Keywords: dotfiles
Platform: UNKNOWN
Classifier: Development Status :: 3 - Alpha
Classifier: Intended Audience :: System Administrators
Classifier: License :: OSI Approved :: MIT License
Classifier: Operating System :: POSIX :: Linux
Classifier: Topic :: Utilities
